{"documentation_our-community.md":"eab265da","documentation_organics.md":"87df3199","documentation_advanced-tools.md":"cf8e328f","documentation_alien-planet.md":"19d8fc43","documentation_structures.md":"b9730314","documentation_assetbrush.md":"a4c8a03a","documentation_basic-tools.md":"c9c0d0d0","documentation_bungeeessentials.md":"d3474e6f","documentation_commands.md":"4fb1b426","documentation_custom.md":"6d9b7730","documentation_getting-around.md":"9b511fdc","documentation_how-to-enter.md":"aa8f0f59","documentation_welcome.md":"6cf2b031","documentation_terrain.md":"a2b30429","index.md":"566dd09b","documentation_plugins.md":"a306d676","documentation_schematics.md":"d3a30992"}
